MANIFEST.in
README
setup.py
toxicbuild/__init__.py
toxicbuild/script.py
toxicbuild.egg-info/PKG-INFO
toxicbuild.egg-info/SOURCES.txt
toxicbuild.egg-info/dependency_links.txt
toxicbuild.egg-info/entry_points.txt
toxicbuild.egg-info/pbr.json
toxicbuild.egg-info/requires.txt
toxicbuild.egg-info/top_level.txt
toxicbuild/common/__init__.py
toxicbuild/common/client.py
toxicbuild/common/exceptions.py
toxicbuild/common/interfaces.py
toxicbuild/common/utils.py
toxicbuild/core/__init__.py
toxicbuild/core/build_config.py
toxicbuild/core/client.py
toxicbuild/core/cmd.py
toxicbuild/core/conf.py
toxicbuild/core/exceptions.py
toxicbuild/core/exchange.py
toxicbuild/core/exchanges.py
toxicbuild/core/mail.py
toxicbuild/core/plugins.py
toxicbuild/core/protocol.py
toxicbuild/core/requests.py
toxicbuild/core/utils.py
toxicbuild/core/vcs.py
toxicbuild/integrations/__init__.py
toxicbuild/integrations/base.py
toxicbuild/integrations/exceptions.py
toxicbuild/integrations/github.py
toxicbuild/integrations/gitlab.py
toxicbuild/integrations/webhook_receivers.py
toxicbuild/integrations/templates/toxicintegrations.conf.tmpl
toxicbuild/master/__init__.py
toxicbuild/master/aws.py
toxicbuild/master/build.py
toxicbuild/master/client.py
toxicbuild/master/consumers.py
toxicbuild/master/coordination.py
toxicbuild/master/document.py
toxicbuild/master/exceptions.py
toxicbuild/master/exchanges.py
toxicbuild/master/hole.py
toxicbuild/master/pollers.py
toxicbuild/master/repository.py
toxicbuild/master/scheduler.py
toxicbuild/master/signals.py
toxicbuild/master/slave.py
toxicbuild/master/users.py
toxicbuild/master/utils.py
toxicbuild/master/templates/toxicmaster.conf.tmpl
toxicbuild/output/__init__.py
toxicbuild/output/exchanges.py
toxicbuild/output/notifications.py
toxicbuild/output/server.py
toxicbuild/output/templates/toxicoutput.conf.tmpl
toxicbuild/slave/__init__.py
toxicbuild/slave/build.py
toxicbuild/slave/docker.py
toxicbuild/slave/exceptions.py
toxicbuild/slave/managers.py
toxicbuild/slave/plugins.py
toxicbuild/slave/protocols.py
toxicbuild/slave/server.py
toxicbuild/slave/templates/toxicslave.conf.tmpl
toxicbuild/ui/__init__.py
toxicbuild/ui/cli.py
toxicbuild/ui/connectors.py
toxicbuild/ui/context_processors.py
