Metadata-Version: 1.1
Name: toxicbuild
Version: 0.7.0
Summary: Simple and flexible continuous integration tool.
Home-page: http://toxicbuild.poraodojuca.net
Author: Juca Crispim
Author-email: juca@poraodojuca.net
License: AGPL
Platform: UNKNOWN
Classifier: Development Status :: 3 - Alpha
Classifier: Environment :: No Input/Output (Daemon)
Classifier: Environment :: Web Environment
Classifier: Intended Audience :: Developers
Classifier: License :: OSI Approved :: GNU General Public License (GPL)
Classifier: Natural Language :: English
Classifier: Operating System :: OS Independent
Classifier: Topic :: Software Development :: Build Tools
Classifier: Topic :: Software Development :: Testing
Provides: toxicbuild
